{
  "name": "smart-gmail-auto-responder-n8n",
  "nodes": [
    {
      "parameters": {
        "pollTimes": {
          "item": [
            {
              "mode": "everyMinute"
            }
          ]
        },
        "filters": {
          "labelIds": "INBOX",
          "q": "=subject:(contact OR query OR support)",
          "readStatus": "unread"
        }
      },
      "type": "n8n-nodes-base.gmailTrigger",
      "typeVersion": 1.3,
      "position": [
        0,
        0
      ],
      "id": "29dd939b-d535-4c7c-8c6d-fbeafef30b0e",
      "name": "Gmail Trigger",
      "credentials": {
        "gmailOAuth2": {
          "id": "6V3bnx1xt38NOXCF",
          "name": "Gmail account"
        }
      }
    },
    {
      "parameters": {
        "conditions": {
          "options": {
            "caseSensitive": true,
            "leftValue": "",
            "typeValidation": "strict",
            "version": 3
          },
          "conditions": [
            {
              "id": "c11e6622-19cd-4aa8-87f8-a99870602f1f",
              "leftValue": "={{ ($json.labels || []).map(l => l.name.toLowerCase()).join(',') }} \n \n",
              "rightValue": "Auto-Replied",
              "operator": {
                "type": "string",
                "operation": "notContains"
              }
            }
          ],
          "combinator": "and"
        },
        "options": {}
      },
      "type": "n8n-nodes-base.if",
      "typeVersion": 2.3,
      "position": [
        224,
        0
      ],
      "id": "3f5674ef-35cc-45ac-b957-c0d306744136",
      "name": "If"
    },
    {
      "parameters": {
        "rules": {
          "values": [
            {
              "conditions": {
                "options": {
                  "caseSensitive": true,
                  "leftValue": "",
                  "typeValidation": "strict",
                  "version": 3
                },
                "conditions": [
                  {
                    "leftValue": "={{ $json.Subject.toLowerCase()}}",
                    "rightValue": "support",
                    "operator": {
                      "type": "string",
                      "operation": "contains"
                    },
                    "id": "30febb7a-a0ce-4379-a394-cb7b25952a20"
                  }
                ],
                "combinator": "and"
              }
            },
            {
              "conditions": {
                "options": {
                  "caseSensitive": true,
                  "leftValue": "",
                  "typeValidation": "strict",
                  "version": 3
                },
                "conditions": [
                  {
                    "id": "56d78efe-7fe4-4e71-b36a-38611fca5b06",
                    "leftValue": "={{ $json.Subject.toLowerCase()}}",
                    "rightValue": "contact",
                    "operator": {
                      "type": "string",
                      "operation": "contains"
                    }
                  }
                ],
                "combinator": "and"
              }
            },
            {
              "conditions": {
                "options": {
                  "caseSensitive": true,
                  "leftValue": "",
                  "typeValidation": "strict",
                  "version": 3
                },
                "conditions": [
                  {
                    "id": "a02e92da-e0b7-4075-a82f-616786f202b6",
                    "leftValue": "={{ $json.Subject.toLowerCase() }}",
                    "rightValue": "career",
                    "operator": {
                      "type": "string",
                      "operation": "contains"
                    }
                  }
                ],
                "combinator": "and"
              }
            }
          ]
        },
        "options": {}
      },
      "type": "n8n-nodes-base.switch",
      "typeVersion": 3.4,
      "position": [
        448,
        -16
      ],
      "id": "aa1e6be1-e28d-4f24-9a59-24a9e332df8b",
      "name": "Switch"
    },
    {
      "parameters": {
        "operation": "reply",
        "messageId": "={{ $json.id }}",
        "message": "=Hello {{ $json.from.name || 'there' }},\n\nThank you for reaching out to us.\n\nWe have received your contact request and our team will review it shortly.\nIf any additional information is required, we’ll get back to you.\n\nBest regards,  \nSupport Team",
        "options": {}
      },
      "type": "n8n-nodes-base.gmail",
      "typeVersion": 2.2,
      "position": [
        672,
        -192
      ],
      "id": "7a4f3c68-5a2e-48c7-bd31-780eed7c2954",
      "name": "Reply to a Support",
      "webhookId": "bc9c8e15-1a96-484b-bd1f-334d38e980c7",
      "credentials": {
        "gmailOAuth2": {
          "id": "6V3bnx1xt38NOXCF",
          "name": "Gmail account"
        }
      }
    },
    {
      "parameters": {
        "operation": "reply",
        "messageId": "={{ $json.id }}",
        "message": "=Hello {{ $json.from.name || 'there' }},  Thank you for contacting us.  We have successfully received your message and it has been forwarded to the concerned team. Our team will review your query and get back to you shortly.  We appreciate your patience.  Best regards,   Team",
        "options": {}
      },
      "type": "n8n-nodes-base.gmail",
      "typeVersion": 2.2,
      "position": [
        672,
        0
      ],
      "id": "162856b0-a93e-4607-96c4-14b3db530101",
      "name": "Reply to Contact",
      "webhookId": "6777953c-3fef-4abc-b38f-4b59b8284e04",
      "credentials": {
        "gmailOAuth2": {
          "id": "6V3bnx1xt38NOXCF",
          "name": "Gmail account"
        }
      }
    },
    {
      "parameters": {
        "operation": "reply",
        "messageId": "={{ $json.id }}",
        "message": "=Hello {{ $json.from.name || 'there' }},  Thank you for your interest in career opportunities with us.  We have received your message and our HR team will review your details. If your profile matches our current requirements, we will reach out to you.  We appreciate your interest in joining our organization.  Best regards,   HR Team",
        "options": {}
      },
      "type": "n8n-nodes-base.gmail",
      "typeVersion": 2.2,
      "position": [
        672,
        192
      ],
      "id": "575a7528-90e5-4b48-9df2-95b9d3e96734",
      "name": "Reply to Career",
      "webhookId": "12afc119-5bf7-4afc-bdb0-8d3bbaa811fd",
      "credentials": {
        "gmailOAuth2": {
          "id": "6V3bnx1xt38NOXCF",
          "name": "Gmail account"
        }
      }
    },
    {
      "parameters": {
        "operation": "addLabels",
        "messageId": "={{ $json.id }}",
        "labelIds": [
          "Label_788686840933740460",
          "Label_7877779778029898154"
        ]
      },
      "type": "n8n-nodes-base.gmail",
      "typeVersion": 2.2,
      "position": [
        896,
        -192
      ],
      "id": "883b5f58-7125-4b9e-b6bd-745af482ac97",
      "name": "Label:Support",
      "webhookId": "51c76cb4-044a-4382-93b2-7cd6fbe7f0c2",
      "credentials": {
        "gmailOAuth2": {
          "id": "6V3bnx1xt38NOXCF",
          "name": "Gmail account"
        }
      }
    },
    {
      "parameters": {
        "operation": "addLabels",
        "messageId": "={{ $json.id }}",
        "labelIds": [
          "Label_788686840933740460",
          "Label_8142043014444094198"
        ]
      },
      "type": "n8n-nodes-base.gmail",
      "typeVersion": 2.2,
      "position": [
        896,
        0
      ],
      "id": "41b9cfd1-253b-4ff0-9b80-3df696f4f874",
      "name": "Label:Contact",
      "webhookId": "508ad11d-b82b-4893-8ffb-2e52ba319cb5",
      "credentials": {
        "gmailOAuth2": {
          "id": "6V3bnx1xt38NOXCF",
          "name": "Gmail account"
        }
      }
    },
    {
      "parameters": {
        "operation": "addLabels",
        "messageId": "={{ $json.id }}",
        "labelIds": [
          "Label_788686840933740460",
          "Label_9050299273583933904"
        ]
      },
      "type": "n8n-nodes-base.gmail",
      "typeVersion": 2.2,
      "position": [
        896,
        192
      ],
      "id": "39b1d076-efa4-464c-8a17-516c5ec1ba8c",
      "name": "Label:Career",
      "webhookId": "b52d670f-ed2e-40f5-b09b-0da3b68279d6",
      "credentials": {
        "gmailOAuth2": {
          "id": "6V3bnx1xt38NOXCF",
          "name": "Gmail account"
        }
      }
    }
  ],
  "pinData": {},
  "connections": {
    "Gmail Trigger": {
      "main": [
        [
          {
            "node": "If",
            "type": "main",
            "index": 0
          }
        ]
      ]
    },
    "If": {
      "main": [
        [
          {
            "node": "Switch",
            "type": "main",
            "index": 0
          }
        ],
        []
      ]
    },
    "Switch": {
      "main": [
        [
          {
            "node": "Reply to a Support",
            "type": "main",
            "index": 0
          }
        ],
        [
          {
            "node": "Reply to Contact",
            "type": "main",
            "index": 0
          }
        ],
        [
          {
            "node": "Reply to Career",
            "type": "main",
            "index": 0
          }
        ]
      ]
    },
    "Reply to a Support": {
      "main": [
        [
          {
            "node": "Label:Support",
            "type": "main",
            "index": 0
          }
        ]
      ]
    },
    "Reply to Contact": {
      "main": [
        [
          {
            "node": "Label:Contact",
            "type": "main",
            "index": 0
          }
        ]
      ]
    },
    "Reply to Career": {
      "main": [
        [
          {
            "node": "Label:Career",
            "type": "main",
            "index": 0
          }
        ]
      ]
    },
    "Label:Support": {
      "main": [
        []
      ]
    },
    "Label:Contact": {
      "main": [
        []
      ]
    },
    "Label:Career": {
      "main": [
        []
      ]
    }
  },
  "active": true,
  "settings": {
    "executionOrder": "v1",
    "availableInMCP": false
  },
  "versionId": "f120e89b-b3c6-4b98-b9bf-6b2d737336ee",
  "meta": {
    "templateCredsSetupCompleted": true,
    "instanceId": "e290f74f7dbc2543fe817dce3a4be64661a9cc791c66e44b5fd34f2cc676cd83"
  },
  "id": "fnJHU6DIxf967Rvn",
  "tags": []
}